{
    "pure": {
        "Curve sketching": 46,
        "Complex numbers": 38,
        "Integration": 37,
        "Differential equation": 35,
        "Coordinate geometry": 32,
        "Trigonometry": 29,
        "Euclidean geometry": 27,
        "Vector geometry": 25,
        "Number theory": 25,
        "Differential equations": 23,
        "Integration by substitution": 22,
        "Analysis": 21,
        "Integral": 19,
        "Groups": 16,
        "Functions": 15,
        "Inequality": 14,
        "Differentiation": 13,
        "Binomial expansion": 12,
        "Vectors": 10,
        "Polar coordinates": 10,
        "Proof by induction": 10,
        "Simultaneous equations": 9,
        "Integration by parts": 9,
        "Matrices": 9,
        "Inequalities": 8,
        "Elementary geometry": 8,
        "Sum": 8,
        "Collision": 8,
        "Polynomials": 8,
        "Complex number": 7,
        "Conic sections": 6,
        "Cubic equation": 6,
        "Integrals": 6,
        "Optimisation": 5,
        "Infinite series": 5,
        "Quadratic equations": 5,
        "Taylor series": 5,
        "Sequences": 5,
        "Cubic equations": 5,
        "Numbers": 4,
        "Series": 4,
        "Difference equation": 4,
        "Hyperbolic functions": 4,
        "Transformation": 4,
        "Polynomial equation": 4,
        "Parametric equations": 4,
        "Parametric equation": 4,
        "Recurrence relations": 4,
        "Projectile motion": 4,
        "Proof": 3,
        "Quadratic equation": 3,
        "3-D geometry": 3,
        "Binomial coefficient": 3,
        "Geometric progression": 3,
        "Roots of polynomials": 3,
        "Approximation": 3,
        "Combinatorics": 3,
        "Recurrence relation": 3,
        "Fibonacci numbers": 3,
        "Surds": 2,
        "Modulo arithmetic": 2,
        "Quadratic function": 2,
        "Polynomial equations": 2,
        "Roots of equations": 2,
        "Modulus function": 2,
        "Transformations": 2,
        "Fluid dynamics": 2,
        "Wedge": 2,
        "Logarithms": 2,
        "Factors of polynomials": 2,
        "Pulley": 2,
        "Maclaurin series": 2,
        "Parabola": 2,
        "Quartic equation": 2,
        "Trigonometric series": 2,
        "Friction": 2,
        "Binomial coefficients": 2,
        "Square roots": 2,
        "Trigonometric equations": 2,
        "Rational Functions": 1,
        "Functional equation": 1,
        "Logic": 1,
        "Proof by Induction": 1,
        "Quadratics": 1,
        "Induction": 1,
        "Geometric sequence": 1,
        "Riemann integration": 1,
        "Curves": 1,
        "Progressions": 1,
        "Infinite product": 1,
        "Spherical polar coordinates": 1,
        "Counting": 1,
        "Magic square": 1,
        "Polynomial factors": 1,
        "Derivative of an integral": 1,
        "Limits": 1,
        "Diamond derivative": 1,
        "Solution of equation": 1,
        "Colonel Blotto": 1,
        "Implicit equation": 1,
        "Sum of series": 1,
        "Linear transformation": 1,
        "Volume and Surface area": 1,
        "Sketching": 1,
        "Financial mathematics": 1,
        "Tour de Clochemerle": 1,
        "Heron's formula": 1,
        "Decimal expansions": 1,
        "Fibonacci number": 1,
        "Circular motion": 1,
        "Area and perimeters": 1,
        "Cubic polynomial": 1,
        "AM-GM inequality": 1,
        "Surface of revolution": 1,
        "e is irrational": 1,
        "Geometric sequences": 1,
        "Limit": 1,
        "Unit fraction": 1,
        "2d Vector product": 1,
        "Area\/Volume of revolution": 1,
        "Hubble's constant": 1,
        "Binomial approximation": 1,
        "Area by integration": 1,
        "Geometric series": 1,
        "Fermat number": 1,
        "Logistic map": 1,
        "Time-distance": 1,
        "Volume of revolution": 1,
        "Solution to equations": 1,
        "Irrational number": 1,
        "Acceleration": 1,
        "Binomial series": 1,
        "Surds and polynomials": 1,
        "Interval bisection": 1,
        "Inclined plane": 1,
        "Solutions of equation": 1,
        "Product": 1,
        "Floor function": 1,
        "Functional equations": 1,
        "Diamond derivatives": 1,
        "Binomial approximations": 1,
        "Jensen's inequality": 1,
        "Convex functions": 1,
        "Chebyshev's theorem": 1,
        "Inverse functions": 1,
        "Chebyshev's polynomial": 1,
        "Centre of mass": 1,
        "Work and Power": 1,
        "Series solutions": 1,
        "Laplace transform": 1,
        "Osculating circle": 1,
        "Integrating factors": 1,
        "Factorisation": 1,
        "Mobius map": 1,
        "Difference equaetions": 1,
        "Ratinoal points": 1,
        "Fibonacci sequence": 1,
        "Integer part": 1,
        "Complex sum": 1,
        "Clock": 1,
        "Variational principle": 1,
        "Curve sketeching": 1,
        "Arctan sum": 1,
        "Complex system": 1,
        "Inequlaities": 1,
        "Area of rectangle in circle segment": 1,
        "Triangles": 1,
        "Sequence": 1,
        "arctan integral": 1,
        "Periodic sequences": 1,
        "Schwarz inequality": 1,
        "Parabola and circle": 1,
        "Inverse square root series": 1,
        "x to the power x to the power x": 1,
        "Car with air and rolling resistance": 1,
        "Inverse cube series": 1,
        "Geomtric mean": 1,
        "Polar equations": 1,
        "Arctan": 1,
        "Ellipse": 1,
        "Trigonometric sums": 1,
        "Area between curve and line": 1,
        "Hyperbola": 1,
        "Sketching an integral function": 1,
        "Polynomials at integer points": 1,
        "Numerical integration": 1,
        "Solving the cubic": 1,
        "Coupled differential equations": 1,
        "Quartic repeated roots": 1,
        "Concave functions": 1,
        "Tan integral": 1,
        "Integration of series": 1,
        "Factorial equations": 1,
        "Triangle intersection": 1,
        "Ant on elastic string": 1,
        "Quadratic roots inequalities": 1,
        "Hermite polynomials": 1,
        "Second order differential equation": 1,
        "Tangent to hyperbola": 1,
        "Arithmetic mean - geometric mean": 1,
        "Complex geometry": 1,
        "Basel series": 1,
        "Integrating fractional part": 1
    },
    "mech": {
        "Projectile motion": 49,
        "Friction": 37,
        "Collision": 37,
        "Circular motion": 22,
        "Equilibrium": 18,
        "Hooke's law": 17,
        "SHM": 12,
        "Time-distance": 9,
        "Pulley": 9,
        "Centre of mass": 6,
        "Poisson distribution": 5,
        "Moment of inertia": 4,
        "Differential equation": 4,
        "Continuous random variable": 4,
        "Energy": 3,
        "Acceleration": 3,
        "Geometrical probability": 3,
        "Pdf": 3,
        "Gravitational force": 2,
        "Gravitational attraction": 2,
        "Work and power": 2,
        "Coin toss": 2,
        "Geometric probability": 2,
        "Inclined plane": 2,
        "Centre of gravity": 2,
        "Elementary probability": 2,
        "Work": 1,
        "Circular Motion": 1,
        "Hooke's Law": 1,
        "Forces": 1,
        "Time-distance graphs": 1,
        "Variable mass": 1,
        "Inextensible string": 1,
        "Work done": 1,
        "Velocity": 1,
        "Elastic strings": 1,
        "Springs and strings": 1,
        "Fluid dynamics": 1,
        "Exponential distribution": 1,
        "Normal distribution": 1,
        "Binomial distribution": 1,
        "How does a chicken cross the road?": 1,
        "Real pendulum": 1,
        "Die": 1,
        "Impulse": 1,
        "Free-fall": 1,
        "Microtus agrestis": 1,
        "Uniform distribution": 1,
        "Air resistance": 1,
        "Vector velocity": 1,
        "Cdf": 1,
        "Hypothesis testing": 1,
        "Balls from bags": 1,
        "Probability with sets": 1,
        "Repulsive force": 1,
        "Ladder": 1,
        "Norman army": 1,
        "Birthday problem": 1,
        "Kinetic energy": 1,
        "Sampling with\/out replacement": 1,
        "Combinatorics": 1,
        "Coordinate geometry": 1,
        "Time-displacement": 1,
        "Friction force": 1,
        "Vector geometry": 1,
        "Skewness": 1,
        "Collision and Friction": 1,
        "Discrete random variables": 1,
        "Bus and rain": 1,
        "Rotating rods": 1,
        "Collisions": 1,
        "Random variable": 1,
        "Elastic string": 1,
        "Kinematics": 1,
        "Static equilibrium: wall and rod": 1,
        "Particle collisions": 1,
        "Projectile and tower": 1,
        "Bullet fired into block": 1,
        "Hanging triangle": 1,
        "Projectile and target": 1,
        "Simple harmonic motion": 1,
        "Motion on a plane": 1,
        "Accelerating car": 1,
        "Colliding particles": 1,
        "Box on inclined plane": 1,
        "Plank on cylinders": 1,
        "Projectile": 1,
        "Game show": 1,
        "Particles connected by spring": 1,
        "Hinged rod": 1,
        "Gun carriage": 1,
        "Motion on two inclined roads": 1,
        "Tension in train coupling": 1,
        "Pulley and rough inclined plane": 1,
        "Beads on wire": 1,
        "Motorbike slipping": 1,
        "Pass the parcel": 1,
        "Particle bouncing": 1,
        "Oscillating disc with point mass": 1,
        "Slack pendulum": 1
    },
    "stats": {
        "Elementary probability": 17,
        "Continuous random variable": 14,
        "Poisson distribution": 12,
        "Discrete random variable": 11,
        "Coin toss": 10,
        "Uniform distribution": 9,
        "Normal distribution": 8,
        "Pdf": 7,
        "Geometrical probability": 7,
        "Tree diagram": 6,
        "Combinatorics": 5,
        "Sampling with\/out replacement": 5,
        "Discrete random variables": 4,
        "Probability density function": 3,
        "Binomial distribution": 3,
        "Lottery": 3,
        "Pgf": 3,
        "Dice": 3,
        "Optimisation": 2,
        "Probability": 2,
        "Expectation": 2,
        "Random walk": 2,
        "Chebyshev's inequality": 2,
        "Independence": 2,
        "Dice roll": 2,
        "Hypothesis testing": 2,
        "Mean and variances": 1,
        "Probability distribution": 1,
        "Difference equation": 1,
        "Poission distribution": 1,
        "Normal and Uniform distribution": 1,
        "Statistics": 1,
        "Graphical probability": 1,
        "Poisson process": 1,
        "Truncated normal distribution": 1,
        "Indicator function": 1,
        "Coding and Cryptography": 1,
        "Moment generating function": 1,
        "Markov chains": 1,
        "Differential equation": 1,
        "Binomial expansion": 1,
        "Algebraic probability": 1,
        "Sampling with replacement": 1,
        "Mathematitis": 1,
        "MLE": 1,
        "Die": 1,
        "Micro-chip": 1,
        "Joint distribution": 1,
        "Combintorics": 1,
        "Harry the Calculating Horse": 1,
        "Elementary particles": 1,
        "Rabbit warren": 1,
        "Microships": 1,
        "Pirates": 1,
        "Approximations": 1,
        "Hobbit and Wizard": 1,
        "Sum of random variables": 1,
        "Pack of cards": 1,
        "Oxtown and Camville": 1,
        "Normal distributions": 1,
        "Coin and sweets": 1,
        "Court of Farnia": 1,
        "Laplace distribution": 1,
        "Sampling without replacement": 1,
        "Andover and Basingstoke Rockets": 1,
        "Corr": 1,
        "Raffle tickets": 1,
        "Integer part": 1,
        "Random integer": 1,
        "Geometric probability": 1,
        "Stirling's approximation": 1,
        "Discrete random distribution": 1,
        "Poisson distributions": 1,
        "Cdf": 1,
        "Gambling": 1,
        "Triangular distribution": 1,
        "Hazard function": 1,
        "Polynomials": 1,
        "Anti-differentiation": 1,
        "Graphs of floor functions": 1,
        "Touching circles": 1,
        "Curvature": 1,
        "Vector geometry": 1,
        "Integer sets": 1,
        "Generating functions": 1,
        "Coin tossing": 1,
        "Internet tester": 1,
        "Coordinate geometry": 1,
        "Factor theorem": 1,
        "Roots of polynomial": 1,
        "Inequalities for rational function ": 1,
        "Binomial identities": 1,
        "Quadratic differential equation": 1,
        "Trigonometric integrals": 1,
        "Approximating sums using integrals": 1,
        "Old hat probability problem": 1,
        "Binomial distribution approximations": 1,
        "Integral reduction": 1,
        "Parabola normals": 1,
        "Integration": 1,
        "Telescoping sums": 1,
        "Prime number distribution": 1,
        "Intersecting curves number": 1,
        "Argand geometry": 1,
        "Functional equations": 1,
        "Kurtosis": 1,
        "Sliced loaf": 1,
        "Fishing": 1,
        "Variance": 1,
        "Coin tosses": 1,
        "Multiple choice questions": 1,
        "Coin toss game": 1,
        "Ordering samples": 1
    }
}